odoo10_addon_l10n_it_invoices_data_communication-10.0.1.1.3-py3.8-nspkg.pth
odoo/addons/l10n_it_invoices_data_communication/README.rst
odoo/addons/l10n_it_invoices_data_communication/__init__.py
odoo/addons/l10n_it_invoices_data_communication/__manifest__.py
odoo/addons/l10n_it_invoices_data_communication/i18n/it.po
odoo/addons/l10n_it_invoices_data_communication/i18n/l10n_it_invoices_data_communication.pot
odoo/addons/l10n_it_invoices_data_communication/models/__init__.py
odoo/addons/l10n_it_invoices_data_communication/models/account.py
odoo/addons/l10n_it_invoices_data_communication/models/account_invoice.py
odoo/addons/l10n_it_invoices_data_communication/models/communication.py
odoo/addons/l10n_it_invoices_data_communication/readme/CONTRIBUTORS.rst
odoo/addons/l10n_it_invoices_data_communication/readme/CREDITS.rst
odoo/addons/l10n_it_invoices_data_communication/readme/DESCRIPTION.rst
odoo/addons/l10n_it_invoices_data_communication/readme/ROADMAP.rst
odoo/addons/l10n_it_invoices_data_communication/security/ir.model.access.csv
odoo/addons/l10n_it_invoices_data_communication/security/security.xml
odoo/addons/l10n_it_invoices_data_communication/static/description/icon.png
odoo/addons/l10n_it_invoices_data_communication/static/description/index.html
odoo/addons/l10n_it_invoices_data_communication/views/account.xml
odoo/addons/l10n_it_invoices_data_communication/views/account_invoice_view.xml
odoo/addons/l10n_it_invoices_data_communication/views/comunicazione.xml
odoo/addons/l10n_it_invoices_data_communication/wizard/__init__.py
odoo/addons/l10n_it_invoices_data_communication/wizard/compute_fiscal_document_type.py
odoo/addons/l10n_it_invoices_data_communication/wizard/compute_fiscal_document_type_view.xml
odoo/addons/l10n_it_invoices_data_communication/wizard/export_file.py
odoo/addons/l10n_it_invoices_data_communication/wizard/export_file_view.xml
odoo/addons/l10n_it_invoices_data_communication/wizard/split_big_communication.py
odoo10_addon_l10n_it_invoices_data_communication-10.0.1.1.3.dist-info/METADATA
odoo10_addon_l10n_it_invoices_data_communication-10.0.1.1.3.dist-info/WHEEL
odoo10_addon_l10n_it_invoices_data_communication-10.0.1.1.3.dist-info/namespace_packages.txt
odoo10_addon_l10n_it_invoices_data_communication-10.0.1.1.3.dist-info/top_level.txt
odoo10_addon_l10n_it_invoices_data_communication-10.0.1.1.3.dist-info/RECORD
